Workbook

Sheet Datos
A1: Ratios financieros bancarios — Santander, BBVA, CaixaBank
A2: Datos brutos extraídos de resultados anuales oficiales (FY2025 / FY2024). Celdas en azul = dato de entrada (hardcoded). Ver columna Notas para fuente exacta de cada fila.
A4: Banco | B4: Año | C4: Beneficio neto atribuido (M€) | D4: Activos totales (M€) | E4: Patrimonio neto (M€) | F4: Margen de intereses (M€) | G4: Margen bruto / Ingresos totales (M€) | H4: Gastos de explotación (M€) | I4: Crédito a la clientela (M€) | J4: Ratio de morosidad oficial (%) | K4: ROE oficial reportado (%) | L4: ROTE oficial reportado (%) | M4: Ratio de eficiencia oficial (%) | N4: CET1 fully loaded (%) | O4: Notas / Fuente
A5: Santander | B5: 2025 | C5: 14101 | D5: 1867515 | E5: 112748 | F5: 42348 | G5: 62390 | H5: 25705 | I5: 1000000 | L5: 0.163 | M5: 0.412 | N5: 0.135 | O5: Beneficio, NII, margen bruto, eficiencia, ROTE y CET1: nota de prensa resultados anuales 2025, santander.com (feb-2026). Gastos de explotación estimados = ratio de eficiencia oficial (41,2%) x margen bruto oficial. Crédito a la clientela aproximado ('cerca de 1 billón de euros' en la nota). Activos y patrimonio: stockanalysis.com (balance consolidado SAN). Morosidad no localizada en fuente abierta — pendiente.
A6: Santander | B6: 2024 | C6: 12590 | D6: 1837081 | E6: 107327 | F6: 43794 | G6: 62390 | L6: 0.155 | O6: Beneficio, NII y ROTE derivados de las variaciones % oficiales reportadas para 2025 (+12%, -3,3%, +0,8pp respectivamente). Margen bruto asumido ~plano respecto a 2025 (el banco lo reportó así). Activos y patrimonio: stockanalysis.com. Gastos de explotación, eficiencia y CET1 2024 no localizados de forma fiable — dejados en blanco.
A7: BBVA | B7: 2025 | C7: 10511 | D7: 859576 | E7: 61796 | F7: 26280 | G7: 36931 | H7: 14332 | J7: 0.027 | L7: 0.193 | M7: 0.388 | N7: 0.127 | O7: Beneficio, NII, margen bruto, gastos, morosidad, ROTE, eficiencia y CET1: nota de prensa resultados 4T2025, accionistaseinversores.bbva.com (feb-2026). Activos y patrimonio: stockanalysis.com (balance consolidado BBVA). Crédito a la clientela: el banco solo reportó variación % (+16,2%), no el importe — dejado en blanco.
A8: BBVA | B8: 2024 | C8: 10059 | D8: 772402 | E8: 60013 | F8: 23074 | G8: 31756 | H8: 12970 | M8: 0.409 | O8: Beneficio, NII, margen bruto y gastos derivados de las variaciones % oficiales reportadas para 2025 (+4,5%, +13,9%, +16,3%, +10,5% respectivamente). Eficiencia 2024 derivada (2025 mejoró 206 p.b.: 38,8% + 2,06% = 40,9%). Activos y patrimonio: stockanalysis.com. Morosidad, ROTE y CET1 2024 no localizados — en blanco.
A9: CaixaBank | B9: 2025 | C9: 5891 | D9: 664040 | E9: 38526 | F9: 10671 | G9: 16270 | H9: 6415 | I9: 384334 | J9: 0.021 | K9: 0.149 | L9: 0.175 | M9: 0.394 | N9: 0.126 | O9: Todos los datos: nota de prensa 'Resultados 2025', caixabank.com. Fila más completa — útil para comprobar tus fórmulas de la hoja Ratios contra el ROE/ROTE/eficiencia que el propio banco reporta.
A10: CaixaBank | B10: 2024 | C10: 5787 | D10: 631003 | E10: 36865 | F10: 11108 | G10: 15873 | H10: 6108 | I10: 361214 | J10: 0.026 | K10: 0.154 | L10: 0.181 | M10: 0.385 | N10: 0.122 | O10: Todos los datos: misma nota de prensa 'Resultados 2025' de CaixaBank (incluye comparativa 2024).

Sheet Ratios
A1: Ratios calculados
A2: Leyenda: la fila verde (CaixaBank 2025) ya está resuelta con fórmulas, como ejemplo — míralas para ver el patrón. Las celdas en AMARILLO son las que tienes que completar tú, con una fórmula que apunte a la hoja 'Datos' (no copies el número, escribe la fórmula).
A4: Banco | B4: Año | C4: ROE = Beneficio neto / Patrimonio neto | D4: ROA = Beneficio neto / Activos totales | E4: Margen de intereses s/ activos (NII / Activos totales) | F4: Ratio de eficiencia = Gastos de explotación / Margen bruto | G4: CET1 (referencia directa desde Datos) | H4: Notas
A5: Santander | B5: 2025 | C5: =Datos!C5/Datos!E5 -> 0.12506652 | D5: =Datos!C5/Datos!D5 -> 0.0075506756 | E5: =Datos!F5/Datos!D5 -> 0.022676123 | F5: =Datos!H5/Datos!G5 -> 0.41200513 | G5: =Datos!N5 -> 0.135
A6: Santander | B6: 2024 | C6: =Datos!C6/Datos!E6 -> 0.11730506 | D6: =Datos!C6/Datos!D6 -> 0.0068532634 | E6: =Datos!F6/Datos!D6 -> 0.023838905
A7: BBVA | B7: 2025 | C7: =Datos!C7/Datos!E7 -> 0.17009192 | D7: =Datos!C7/Datos!D7 -> 0.012228122 | E7: =Datos!F7/Datos!D7 -> 0.030573213 | F7: =Datos!H7/Datos!G7 -> 0.38807506 | G7: =Datos!N7 -> 0.127
A8: BBVA | B8: 2024 | C8: =Datos!C8/Datos!E8 -> 0.16761368 | D8: =Datos!C8/Datos!D8 -> 0.013023011 | E8: =Datos!F8/Datos!D8 -> 0.029873045 | F8: =Datos!H8/Datos!G8 -> 0.40842675
A9: CaixaBank | B9: 2025 | C9: =Datos!C9/Datos!E9 -> 0.15290972 | D9: =Datos!C9/Datos!D9 -> 0.0088714535 | E9: =Datos!F9/Datos!D9 -> 0.016069815 | F9: =Datos!H9/Datos!G9 -> 0.39428396 | G9: =Datos!N9 -> 0.126 | H9: Ejemplo resuelto — compáralo con el ROE/ROTE/eficiencia oficiales de la hoja Datos.
A10: CaixaBank | B10: 2024 | C10: =Datos!C10/Datos!E10 -> 0.15697816 | D10: =Datos!C10/Datos!D10 -> 0.0091711133 | E10: =Datos!F10/Datos!D10 -> 0.01760372 | F10: =Datos!H10/Datos!G10 -> 0.38480438 | G10: =Datos!N10 -> 0.122

Sheet Datos-Largos
A1: Banco | B1: Año | C1: Métrica | D1: Valor
A2: Santander | B2: 2025 | C2: ROE | D2: 0.125
A3: Santander | B3: 2025 | C3: ROA | D3: 0.008
A4: Santander | B4: 2025 | C4: Margen de intereses s/activos | D4: 0.023
A5: Santander | B5: 2025 | C5: Ratio de eficiencia | D5: 0.412
A6: Santander | B6: 2025 | C6: CET1 | D6: 0.135
A7: Santander | B7: 2024 | C7: ROE | D7: 0.117
A8: Santander | B8: 2024 | C8: ROA | D8: 0.007
A9: Santander | B9: 2024 | C9: Margen de intereses s/activos | D9: 0.024
A10: BBVA | B10: 2025 | C10: ROE | D10: 0.17
A11: BBVA | B11: 2025 | C11: ROA | D11: 0.012
A12: BBVA | B12: 2025 | C12: Margen de intereses s/activos | D12: 0.031
A13: BBVA | B13: 2025 | C13: Ratio de eficiencia | D13: 0.388
... A28: CaixaBank | B28: 2024 | C28: CET1 | D28: 0.122

Sheet Tabla dinamica 
A1: Año | B1: 2025
A3: Suma de Valor | B3: Métrica
A4: Banco | B4: CET1 | C4: Margen de intereses s/activos | D4: Ratio de eficiencia | E4: ROA | F4: ROE
A5: BBVA | B5: 0.127 | C5: 0.031 | D5: 0.388 | E5: 0.012 | F5: 0.17
A6: CaixaBank | B6: 0.126 | C6: 0.016 | D6: 0.394 | E6: 0.009 | F6: 0.153
A7: Santander | B7: 0.135 | C7: 0.023 | D7: 0.412 | E7: 0.008 | F7: 0.125

Sheet Resumen ejecutivo
A1: Resumen ejecutivo — Ratios 2025
A3: Banco | B3: ROE | C3: ROA | D3: Margen de intereses s/activos | E3: Ratio de eficiencia | F3: CET 1
A5: Santander | B5: =Ratios!C5 -> 0.12506652 | C5: =Ratios!D5 -> 0.0075506756 | D5: =Ratios!E5 -> 0.022676123 | E5: =Ratios!F5 -> 0.41200513 | F5: =Ratios!G5 -> 0.135
A7: BBVA | B7: =Ratios!C7 -> 0.17009192 | C7: =Ratios!D7 -> 0.012228122 | D7: =Ratios!E7 -> 0.030573213 | E7: =Ratios!F7 -> 0.38807506 | F7: =Ratios!G7 -> 0.127
A9: CaixaBank | B9: =Ratios!C9 -> 0.15290972 | C9: =Ratios!D9 -> 0.0088714535 | D9: =Ratios!E9 -> 0.016069815 | E9: =Ratios!F9 -> 0.39428396 | F9: =Ratios!G9 -> 0.126
A11: BBVA es el banco que mejor rinde en 2025: el ROE y el ROA más altos de los tres, y además el que menos gasta por cada euro que gana (ratio de eficiencia más bajo). Santander va por detrás en rentabilidad, pero tiene el CET1 más alto, así que es el que más colchón de capital guarda por si vienen mal dadas. CaixaBank se queda en un punto intermedio en casi todo, sin destacar ni quedar mal en ningún ratio.
